telescoop_auth/__init__.py
telescoop_auth/admin.py
telescoop_auth/apps.py
telescoop_auth/emails.py
telescoop_auth/managers.py
telescoop_auth/models.py
telescoop_auth/serializers.py
telescoop_auth/tests.py
telescoop_auth/urls.py
telescoop_auth/views.py
telescoop_auth/migrations/0001_initial.py
telescoop_auth/migrations/0002_alter_user_id.py
telescoop_auth/migrations/0003_user_is_superuser.py
telescoop_auth/migrations/0004_user_created_user_modified_alter_user_is_active.py
telescoop_auth/migrations/__init__.py
telescoop_auth-0.0.8.dist-info/LICENSE
telescoop_auth-0.0.8.dist-info/METADATA
telescoop_auth-0.0.8.dist-info/WHEEL
telescoop_auth-0.0.8.dist-info/top_level.txt
telescoop_auth-0.0.8.dist-info/RECORD
